README.txt
setup.py
liblockfile/__init__.py
python_liblockfile.egg-info/PKG-INFO
python_liblockfile.egg-info/SOURCES.txt
python_liblockfile.egg-info/dependency_links.txt
python_liblockfile.egg-info/top_level.txt