Metadata-Version: 1.1
Name: python-liblockfile
Version: 0.2
Summary: A wrapper around liblockfile, using ctypes.
Home-page: https://launchpad.net/python-liblockfile
Author: Gavin Panella
Author-email: gavin.panella@canonical.com
License: UNKNOWN
Platform: UNKNOWN
Classifier: Development Status :: 5 - Production/Stable
Classifier: Intended Audience :: Developers
Classifier: Intended Audience :: System Administrators
Classifier: Programming Language :: Python :: 3
Classifier: Programming Language :: Python
Classifier: Topic :: Software Development :: Libraries
